{
  "id": "163f8a38-f5d3-41e7-9089-183d257287c5",
  "prevId": "00000000-0000-0000-0000-000000000000",
  "version": "7",
  "dialect": "postgresql",
  "tables": {
    "public.blogs": {
      "name": "blogs",
      "schema": "",
      "columns": {
        "id": {
          "name": "id",
          "type": "uuid",
          "primaryKey": true,
          "notNull": true,
          "default": "gen_random_uuid()"
        },
        "author_id": {
          "name": "author_id",
          "type": "uuid",
          "primaryKey": false,
          "notNull": true
        },
        "type": {
          "name": "type",
          "type": "blog_type",
          "typeSchema": "public",
          "primaryKey": false,
          "notNull": true,
          "default": "'editorial'"
        },
        "status": {
          "name": "status",
          "type": "blog_status",
          "typeSchema": "public",
          "primaryKey": false,
          "notNull": true,
          "default": "'draft'"
        },
        "title": {
          "name": "title",
          "type": "varchar(255)",
          "primaryKey": false,
          "notNull": true
        },
        "title_en": {
          "name": "title_en",
          "type": "varchar(255)",
          "primaryKey": false,
          "notNull": false
        },
        "slug": {
          "name": "slug",
          "type": "varchar(255)",
          "primaryKey": false,
          "notNull": true
        },
        "slug_en": {
          "name": "slug_en",
          "type": "varchar(255)",
          "primaryKey": false,
          "notNull": false
        },
        "content": {
          "name": "content",
          "type": "text",
          "primaryKey": false,
          "notNull": true
        },
        "content_en": {
          "name": "content_en",
          "type": "text",
          "primaryKey": false,
          "notNull": false
        },
        "excerpt": {
          "name": "excerpt",
          "type": "text",
          "primaryKey": false,
          "notNull": false
        },
        "excerpt_en": {
          "name": "excerpt_en",
          "type": "text",
          "primaryKey": false,
          "notNull": false
        },
        "meta_title": {
          "name": "meta_title",
          "type": "varchar(255)",
          "primaryKey": false,
          "notNull": false
        },
        "meta_title_en": {
          "name": "meta_title_en",
          "type": "varchar(255)",
          "primaryKey": false,
          "notNull": false
        },
        "meta_description": {
          "name": "meta_description",
          "type": "varchar(500)",
          "primaryKey": false,
          "notNull": false
        },
        "meta_description_en": {
          "name": "meta_description_en",
          "type": "varchar(500)",
          "primaryKey": false,
          "notNull": false
        },
        "featured_image": {
          "name": "featured_image",
          "type": "varchar(500)",
          "primaryKey": false,
          "notNull": false
        },
        "images": {
          "name": "images",
          "type": "jsonb",
          "primaryKey": false,
          "notNull": false
        },
        "categories": {
          "name": "categories",
          "type": "jsonb",
          "primaryKey": false,
          "notNull": false
        },
        "tags": {
          "name": "tags",
          "type": "jsonb",
          "primaryKey": false,
          "notNull": false
        },
        "view_count": {
          "name": "view_count",
          "type": "text",
          "primaryKey": false,
          "notNull": false,
          "default": "'0'"
        },
        "read_time": {
          "name": "read_time",
          "type": "text",
          "primaryKey": false,
          "notNull": false
        },
        "is_featured": {
          "name": "is_featured",
          "type": "boolean",
          "primaryKey": false,
          "notNull": true,
          "default": false
        },
        "featured_order": {
          "name": "featured_order",
          "type": "text",
          "primaryKey": false,
          "notNull": false,
          "default": "'0'"
        },
        "related_places": {
          "name": "related_places",
          "type": "jsonb",
          "primaryKey": false,
          "notNull": false
        },
        "related_blogs": {
          "name": "related_blogs",
          "type": "jsonb",
          "primaryKey": false,
          "notNull": false
        },
        "published_at": {
          "name": "published_at",
          "type": "timestamp with time zone",
          "primaryKey": false,
          "notNull": false
        },
        "scheduled_at": {
          "name": "scheduled_at",
          "type": "timestamp with time zone",
          "primaryKey": false,
          "notNull": false
        },
        "admin_notes": {
          "name": "admin_notes",
          "type": "text",
          "primaryKey": false,
          "notNull": false
        },
        "rejection_reason": {
          "name": "rejection_reason",
          "type": "text",
          "primaryKey": false,
          "notNull": false
        },
        "moderated_by": {
          "name": "moderated_by",
          "type": "uuid",
          "primaryKey": false,
          "notNull": false
        },
        "moderated_at": {
          "name": "moderated_at",
          "type": "timestamp with time zone",
          "primaryKey": false,
          "notNull": false
        },
        "created_at": {
          "name": "created_at",
          "type": "timestamp with time zone",
          "primaryKey": false,
          "notNull": true,
          "default": "now()"
        },
        "updated_at": {
          "name": "updated_at",
          "type": "timestamp with time zone",
          "primaryKey": false,
          "notNull": true,
          "default": "now()"
        }
      },
      "indexes": {
        "blogs_author_id_idx": {
          "name": "blogs_author_id_idx",
          "columns": [
            {
              "expression": "author_id",
              "isExpression": false,
              "asc": true,
              "nulls": "last"
            }
          ],
          "isUnique": false,
          "concurrently": false,
          "method": "btree",
          "with": {}
        },
        "blogs_status_idx": {
          "name": "blogs_status_idx",
          "columns": [
            {
              "expression": "status",
              "isExpression": false,
              "asc": true,
              "nulls": "last"
            }
          ],
          "isUnique": false,
          "concurrently": false,
          "method": "btree",
          "with": {}
        },
        "blogs_type_idx": {
          "name": "blogs_type_idx",
          "columns": [
            {
              "expression": "type",
              "isExpression": false,
              "asc": true,
              "nulls": "last"
            }
          ],
          "isUnique": false,
          "concurrently": false,
          "method": "btree",
          "with": {}
        },
        "blogs_slug_idx": {
          "name": "blogs_slug_idx",
          "columns": [
            {
              "expression": "slug",
              "isExpression": false,
              "asc": true,
              "nulls": "last"
            }
          ],
          "isUnique": false,
          "concurrently": false,
          "method": "btree",
          "with": {}
        },
        "blogs_slug_en_idx": {
          "name": "blogs_slug_en_idx",
          "columns": [
            {
              "expression": "slug_en",
              "isExpression": false,
              "asc": true,
              "nulls": "last"
            }
          ],
          "isUnique": false,
          "concurrently": false,
          "method": "btree",
          "with": {}
        },
        "blogs_featured_idx": {
          "name": "blogs_featured_idx",
          "columns": [
            {
              "expression": "is_featured",
              "isExpression": false,
              "asc": true,
              "nulls": "last"
            },
            {
              "expression": "featured_order",
              "isExpression": false,
              "asc": true,
              "nulls": "last"
            }
          ],
          "isUnique": false,
          "concurrently": false,
          "method": "btree",
          "with": {}
        },
        "blogs_published_idx": {
          "name": "blogs_published_idx",
          "columns": [
            {
              "expression": "published_at",
              "isExpression": false,
              "asc": true,
              "nulls": "last"
            }
          ],
          "isUnique": false,
          "concurrently": false,
          "method": "btree",
          "with": {}
        }
      },
      "foreignKeys": {
        "blogs_author_id_users_id_fk": {
          "name": "blogs_author_id_users_id_fk",
          "tableFrom": "blogs",
          "tableTo": "users",
          "columnsFrom": [
            "author_id"
          ],
          "columnsTo": [
            "id"
          ],
          "onDelete": "no action",
          "onUpdate": "no action"
        },
        "blogs_moderated_by_users_id_fk": {
          "name": "blogs_moderated_by_users_id_fk",
          "tableFrom": "blogs",
          "tableTo": "users",
          "columnsFrom": [
            "moderated_by"
          ],
          "columnsTo": [
            "id"
          ],
          "onDelete": "no action",
          "onUpdate": "no action"
        }
      },
      "compositePrimaryKeys": {},
      "uniqueConstraints": {
        "blogs_slug_unique": {
          "name": "blogs_slug_unique",
          "nullsNotDistinct": false,
          "columns": [
            "slug"
          ]
        },
        "blogs_slug_en_unique": {
          "name": "blogs_slug_en_unique",
          "nullsNotDistinct": false,
          "columns": [
            "slug_en"
          ]
        }
      },
      "policies": {},
      "checkConstraints": {},
      "isRLSEnabled": false
    },
    "public.collections": {
      "name": "collections",
      "schema": "",
      "columns": {
        "id": {
          "name": "id",
          "type": "uuid",
          "primaryKey": true,
          "notNull": true,
          "default": "gen_random_uuid()"
        },
        "created_by": {
          "name": "created_by",
          "type": "uuid",
          "primaryKey": false,
          "notNull": true
        },
        "name": {
          "name": "name",
          "type": "varchar(255)",
          "primaryKey": false,
          "notNull": true
        },
        "name_en": {
          "name": "name_en",
          "type": "varchar(255)",
          "primaryKey": false,
          "notNull": false
        },
        "slug": {
          "name": "slug",
          "type": "varchar(255)",
          "primaryKey": false,
          "notNull": true
        },
        "slug_en": {
          "name": "slug_en",
          "type": "varchar(255)",
          "primaryKey": false,
          "notNull": false
        },
        "description": {
          "name": "description",
          "type": "text",
          "primaryKey": false,
          "notNull": false
        },
        "description_en": {
          "name": "description_en",
          "type": "text",
          "primaryKey": false,
          "notNull": false
        },
        "short_description": {
          "name": "short_description",
          "type": "varchar(500)",
          "primaryKey": false,
          "notNull": false
        },
        "short_description_en": {
          "name": "short_description_en",
          "type": "varchar(500)",
          "primaryKey": false,
          "notNull": false
        },
        "meta_title": {
          "name": "meta_title",
          "type": "varchar(255)",
          "primaryKey": false,
          "notNull": false
        },
        "meta_title_en": {
          "name": "meta_title_en",
          "type": "varchar(255)",
          "primaryKey": false,
          "notNull": false
        },
        "meta_description": {
          "name": "meta_description",
          "type": "varchar(500)",
          "primaryKey": false,
          "notNull": false
        },
        "meta_description_en": {
          "name": "meta_description_en",
          "type": "varchar(500)",
          "primaryKey": false,
          "notNull": false
        },
        "featured_image": {
          "name": "featured_image",
          "type": "varchar(500)",
          "primaryKey": false,
          "notNull": false
        },
        "images": {
          "name": "images",
          "type": "jsonb",
          "primaryKey": false,
          "notNull": false
        },
        "is_public": {
          "name": "is_public",
          "type": "boolean",
          "primaryKey": false,
          "notNull": true,
          "default": true
        },
        "is_featured": {
          "name": "is_featured",
          "type": "boolean",
          "primaryKey": false,
          "notNull": true,
          "default": false
        },
        "featured_order": {
          "name": "featured_order",
          "type": "text",
          "primaryKey": false,
          "notNull": false,
          "default": "'0'"
        },
        "place_ids": {
          "name": "place_ids",
          "type": "jsonb",
          "primaryKey": false,
          "notNull": false
        },
        "blog_ids": {
          "name": "blog_ids",
          "type": "jsonb",
          "primaryKey": false,
          "notNull": false
        },
        "tags": {
          "name": "tags",
          "type": "jsonb",
          "primaryKey": false,
          "notNull": false
        },
        "created_at": {
          "name": "created_at",
          "type": "timestamp with time zone",
          "primaryKey": false,
          "notNull": true,
          "default": "now()"
        },
        "updated_at": {
          "name": "updated_at",
          "type": "timestamp with time zone",
          "primaryKey": false,
          "notNull": true,
          "default": "now()"
        }
      },
      "indexes": {
        "collections_created_by_idx": {
          "name": "collections_created_by_idx",
          "columns": [
            {
              "expression": "created_by",
              "isExpression": false,
              "asc": true,
              "nulls": "last"
            }
          ],
          "isUnique": false,
          "concurrently": false,
          "method": "btree",
          "with": {}
        },
        "collections_slug_idx": {
          "name": "collections_slug_idx",
          "columns": [
            {
              "expression": "slug",
              "isExpression": false,
              "asc": true,
              "nulls": "last"
            }
          ],
          "isUnique": false,
          "concurrently": false,
          "method": "btree",
          "with": {}
        },
        "collections_slug_en_idx": {
          "name": "collections_slug_en_idx",
          "columns": [
            {
              "expression": "slug_en",
              "isExpression": false,
              "asc": true,
              "nulls": "last"
            }
          ],
          "isUnique": false,
          "concurrently": false,
          "method": "btree",
          "with": {}
        },
        "collections_featured_idx": {
          "name": "collections_featured_idx",
          "columns": [
            {
              "expression": "is_featured",
              "isExpression": false,
              "asc": true,
              "nulls": "last"
            },
            {
              "expression": "featured_order",
              "isExpression": false,
              "asc": true,
              "nulls": "last"
            }
          ],
          "isUnique": false,
          "concurrently": false,
          "method": "btree",
          "with": {}
        },
        "collections_public_idx": {
          "name": "collections_public_idx",
          "columns": [
            {
              "expression": "is_public",
              "isExpression": false,
              "asc": true,
              "nulls": "last"
            }
          ],
          "isUnique": false,
          "concurrently": false,
          "method": "btree",
          "with": {}
        }
      },
      "foreignKeys": {
        "collections_created_by_users_id_fk": {
          "name": "collections_created_by_users_id_fk",
          "tableFrom": "collections",
          "tableTo": "users",
          "columnsFrom": [
            "created_by"
          ],
          "columnsTo": [
            "id"
          ],
          "onDelete": "no action",
          "onUpdate": "no action"
        }
      },
      "compositePrimaryKeys": {},
      "uniqueConstraints": {
        "collections_slug_unique": {
          "name": "collections_slug_unique",
          "nullsNotDistinct": false,
          "columns": [
            "slug"
          ]
        },
        "collections_slug_en_unique": {
          "name": "collections_slug_en_unique",
          "nullsNotDistinct": false,
          "columns": [
            "slug_en"
          ]
        }
      },
      "policies": {},
      "checkConstraints": {},
      "isRLSEnabled": false
    },
    "public.users": {
      "name": "users",
      "schema": "",
      "columns": {
        "id": {
          "name": "id",
          "type": "uuid",
          "primaryKey": true,
          "notNull": true,
          "default": "gen_random_uuid()"
        },
        "email": {
          "name": "email",
          "type": "varchar(255)",
          "primaryKey": false,
          "notNull": true
        },
        "password_hash": {
          "name": "password_hash",
          "type": "varchar(255)",
          "primaryKey": false,
          "notNull": true
        },
        "first_name": {
          "name": "first_name",
          "type": "varchar(100)",
          "primaryKey": false,
          "notNull": true
        },
        "last_name": {
          "name": "last_name",
          "type": "varchar(100)",
          "primaryKey": false,
          "notNull": true
        },
        "phone": {
          "name": "phone",
          "type": "varchar(20)",
          "primaryKey": false,
          "notNull": false
        },
        "user_type": {
          "name": "user_type",
          "type": "user_type",
          "typeSchema": "public",
          "primaryKey": false,
          "notNull": true,
          "default": "'traveler'"
        },
        "status": {
          "name": "status",
          "type": "user_status",
          "typeSchema": "public",
          "primaryKey": false,
          "notNull": true,
          "default": "'active'"
        },
        "language_preference": {
          "name": "language_preference",
          "type": "varchar(5)",
          "primaryKey": false,
          "notNull": true,
          "default": "'tr'"
        },
        "email_verified": {
          "name": "email_verified",
          "type": "boolean",
          "primaryKey": false,
          "notNull": true,
          "default": false
        },
        "email_verified_at": {
          "name": "email_verified_at",
          "type": "timestamp with time zone",
          "primaryKey": false,
          "notNull": false
        },
        "last_login_at": {
          "name": "last_login_at",
          "type": "timestamp with time zone",
          "primaryKey": false,
          "notNull": false
        },
        "created_at": {
          "name": "created_at",
          "type": "timestamp with time zone",
          "primaryKey": false,
          "notNull": true,
          "default": "now()"
        },
        "updated_at": {
          "name": "updated_at",
          "type": "timestamp with time zone",
          "primaryKey": false,
          "notNull": true,
          "default": "now()"
        }
      },
      "indexes": {},
      "foreignKeys": {},
      "compositePrimaryKeys": {},
      "uniqueConstraints": {
        "users_email_unique": {
          "name": "users_email_unique",
          "nullsNotDistinct": false,
          "columns": [
            "email"
          ]
        }
      },
      "policies": {},
      "checkConstraints": {},
      "isRLSEnabled": false
    },
    "public.places": {
      "name": "places",
      "schema": "",
      "columns": {
        "id": {
          "name": "id",
          "type": "uuid",
          "primaryKey": true,
          "notNull": true,
          "default": "gen_random_uuid()"
        },
        "owner_id": {
          "name": "owner_id",
          "type": "uuid",
          "primaryKey": false,
          "notNull": true
        },
        "type": {
          "name": "type",
          "type": "place_type",
          "typeSchema": "public",
          "primaryKey": false,
          "notNull": true
        },
        "status": {
          "name": "status",
          "type": "place_status",
          "typeSchema": "public",
          "primaryKey": false,
          "notNull": true,
          "default": "'draft'"
        },
        "name": {
          "name": "name",
          "type": "varchar(255)",
          "primaryKey": false,
          "notNull": true
        },
        "name_en": {
          "name": "name_en",
          "type": "varchar(255)",
          "primaryKey": false,
          "notNull": false
        },
        "slug": {
          "name": "slug",
          "type": "varchar(255)",
          "primaryKey": false,
          "notNull": true
        },
        "slug_en": {
          "name": "slug_en",
          "type": "varchar(255)",
          "primaryKey": false,
          "notNull": false
        },
        "description": {
          "name": "description",
          "type": "text",
          "primaryKey": false,
          "notNull": true
        },
        "description_en": {
          "name": "description_en",
          "type": "text",
          "primaryKey": false,
          "notNull": false
        },
        "short_description": {
          "name": "short_description",
          "type": "varchar(500)",
          "primaryKey": false,
          "notNull": false
        },
        "short_description_en": {
          "name": "short_description_en",
          "type": "varchar(500)",
          "primaryKey": false,
          "notNull": false
        },
        "address": {
          "name": "address",
          "type": "text",
          "primaryKey": false,
          "notNull": true
        },
        "address_en": {
          "name": "address_en",
          "type": "text",
          "primaryKey": false,
          "notNull": false
        },
        "city": {
          "name": "city",
          "type": "varchar(100)",
          "primaryKey": false,
          "notNull": true
        },
        "district": {
          "name": "district",
          "type": "varchar(100)",
          "primaryKey": false,
          "notNull": false
        },
        "postal_code": {
          "name": "postal_code",
          "type": "varchar(10)",
          "primaryKey": false,
          "notNull": false
        },
        "latitude": {
          "name": "latitude",
          "type": "numeric(10, 7)",
          "primaryKey": false,
          "notNull": true
        },
        "longitude": {
          "name": "longitude",
          "type": "numeric(10, 7)",
          "primaryKey": false,
          "notNull": true
        },
        "phone": {
          "name": "phone",
          "type": "varchar(20)",
          "primaryKey": false,
          "notNull": false
        },
        "email": {
          "name": "email",
          "type": "varchar(255)",
          "primaryKey": false,
          "notNull": false
        },
        "website": {
          "name": "website",
          "type": "varchar(500)",
          "primaryKey": false,
          "notNull": false
        },
        "type_specific_data": {
          "name": "type_specific_data",
          "type": "jsonb",
          "primaryKey": false,
          "notNull": false
        },
        "meta_title": {
          "name": "meta_title",
          "type": "varchar(255)",
          "primaryKey": false,
          "notNull": false
        },
        "meta_title_en": {
          "name": "meta_title_en",
          "type": "varchar(255)",
          "primaryKey": false,
          "notNull": false
        },
        "meta_description": {
          "name": "meta_description",
          "type": "varchar(500)",
          "primaryKey": false,
          "notNull": false
        },
        "meta_description_en": {
          "name": "meta_description_en",
          "type": "varchar(500)",
          "primaryKey": false,
          "notNull": false
        },
        "featured_image": {
          "name": "featured_image",
          "type": "varchar(500)",
          "primaryKey": false,
          "notNull": false
        },
        "images": {
          "name": "images",
          "type": "jsonb",
          "primaryKey": false,
          "notNull": false
        },
        "price_range": {
          "name": "price_range",
          "type": "varchar(50)",
          "primaryKey": false,
          "notNull": false
        },
        "average_price": {
          "name": "average_price",
          "type": "numeric(10, 2)",
          "primaryKey": false,
          "notNull": false
        },
        "currency": {
          "name": "currency",
          "type": "varchar(3)",
          "primaryKey": false,
          "notNull": false,
          "default": "'TRY'"
        },
        "amenities": {
          "name": "amenities",
          "type": "jsonb",
          "primaryKey": false,
          "notNull": false
        },
        "tags": {
          "name": "tags",
          "type": "jsonb",
          "primaryKey": false,
          "notNull": false
        },
        "admin_notes": {
          "name": "admin_notes",
          "type": "text",
          "primaryKey": false,
          "notNull": false
        },
        "rejection_reason": {
          "name": "rejection_reason",
          "type": "text",
          "primaryKey": false,
          "notNull": false
        },
        "view_count": {
          "name": "view_count",
          "type": "numeric(10, 0)",
          "primaryKey": false,
          "notNull": false,
          "default": "'0'"
        },
        "last_viewed_at": {
          "name": "last_viewed_at",
          "type": "timestamp with time zone",
          "primaryKey": false,
          "notNull": false
        },
        "approved_at": {
          "name": "approved_at",
          "type": "timestamp with time zone",
          "primaryKey": false,
          "notNull": false
        },
        "published_at": {
          "name": "published_at",
          "type": "timestamp with time zone",
          "primaryKey": false,
          "notNull": false
        },
        "created_at": {
          "name": "created_at",
          "type": "timestamp with time zone",
          "primaryKey": false,
          "notNull": true,
          "default": "now()"
        },
        "updated_at": {
          "name": "updated_at",
          "type": "timestamp with time zone",
          "primaryKey": false,
          "notNull": true,
          "default": "now()"
        }
      },
      "indexes": {
        "places_owner_id_idx": {
          "name": "places_owner_id_idx",
          "columns": [
            {
              "expression": "owner_id",
              "isExpression": false,
              "asc": true,
              "nulls": "last"
            }
          ],
          "isUnique": false,
          "concurrently": false,
          "method": "btree",
          "with": {}
        },
        "places_type_idx": {
          "name": "places_type_idx",
          "columns": [
            {
              "expression": "type",
              "isExpression": false,
              "asc": true,
              "nulls": "last"
            }
          ],
          "isUnique": false,
          "concurrently": false,
          "method": "btree",
          "with": {}
        },
        "places_status_idx": {
          "name": "places_status_idx",
          "columns": [
            {
              "expression": "status",
              "isExpression": false,
              "asc": true,
              "nulls": "last"
            }
          ],
          "isUnique": false,
          "concurrently": false,
          "method": "btree",
          "with": {}
        },
        "places_location_idx": {
          "name": "places_location_idx",
          "columns": [
            {
              "expression": "latitude",
              "isExpression": false,
              "asc": true,
              "nulls": "last"
            },
            {
              "expression": "longitude",
              "isExpression": false,
              "asc": true,
              "nulls": "last"
            }
          ],
          "isUnique": false,
          "concurrently": false,
          "method": "btree",
          "with": {}
        },
        "places_slug_idx": {
          "name": "places_slug_idx",
          "columns": [
            {
              "expression": "slug",
              "isExpression": false,
              "asc": true,
              "nulls": "last"
            }
          ],
          "isUnique": false,
          "concurrently": false,
          "method": "btree",
          "with": {}
        },
        "places_slug_en_idx": {
          "name": "places_slug_en_idx",
          "columns": [
            {
              "expression": "slug_en",
              "isExpression": false,
              "asc": true,
              "nulls": "last"
            }
          ],
          "isUnique": false,
          "concurrently": false,
          "method": "btree",
          "with": {}
        }
      },
      "foreignKeys": {
        "places_owner_id_users_id_fk": {
          "name": "places_owner_id_users_id_fk",
          "tableFrom": "places",
          "tableTo": "users",
          "columnsFrom": [
            "owner_id"
          ],
          "columnsTo": [
            "id"
          ],
          "onDelete": "no action",
          "onUpdate": "no action"
        }
      },
      "compositePrimaryKeys": {},
      "uniqueConstraints": {
        "places_slug_unique": {
          "name": "places_slug_unique",
          "nullsNotDistinct": false,
          "columns": [
            "slug"
          ]
        },
        "places_slug_en_unique": {
          "name": "places_slug_en_unique",
          "nullsNotDistinct": false,
          "columns": [
            "slug_en"
          ]
        }
      },
      "policies": {},
      "checkConstraints": {},
      "isRLSEnabled": false
    },
    "public.subscription_plans": {
      "name": "subscription_plans",
      "schema": "",
      "columns": {
        "id": {
          "name": "id",
          "type": "uuid",
          "primaryKey": true,
          "notNull": true,
          "default": "gen_random_uuid()"
        },
        "name": {
          "name": "name",
          "type": "varchar(100)",
          "primaryKey": false,
          "notNull": true
        },
        "name_en": {
          "name": "name_en",
          "type": "varchar(100)",
          "primaryKey": false,
          "notNull": false
        },
        "description": {
          "name": "description",
          "type": "text",
          "primaryKey": false,
          "notNull": false
        },
        "description_en": {
          "name": "description_en",
          "type": "text",
          "primaryKey": false,
          "notNull": false
        },
        "plan_type": {
          "name": "plan_type",
          "type": "plan_type",
          "typeSchema": "public",
          "primaryKey": false,
          "notNull": true
        },
        "monthly_price": {
          "name": "monthly_price",
          "type": "numeric(10, 2)",
          "primaryKey": false,
          "notNull": true
        },
        "yearly_price": {
          "name": "yearly_price",
          "type": "numeric(10, 2)",
          "primaryKey": false,
          "notNull": false
        },
        "currency": {
          "name": "currency",
          "type": "varchar(3)",
          "primaryKey": false,
          "notNull": true,
          "default": "'TRY'"
        },
        "features": {
          "name": "features",
          "type": "jsonb",
          "primaryKey": false,
          "notNull": false
        },
        "max_listings": {
          "name": "max_listings",
          "type": "text",
          "primaryKey": false,
          "notNull": false,
          "default": "'1'"
        },
        "max_images": {
          "name": "max_images",
          "type": "text",
          "primaryKey": false,
          "notNull": false,
          "default": "'10'"
        },
        "max_blog_posts": {
          "name": "max_blog_posts",
          "type": "text",
          "primaryKey": false,
          "notNull": false,
          "default": "'5'"
        },
        "is_active": {
          "name": "is_active",
          "type": "boolean",
          "primaryKey": false,
          "notNull": true,
          "default": true
        },
        "sort_order": {
          "name": "sort_order",
          "type": "text",
          "primaryKey": false,
          "notNull": false,
          "default": "'0'"
        },
        "created_at": {
          "name": "created_at",
          "type": "timestamp with time zone",
          "primaryKey": false,
          "notNull": true,
          "default": "now()"
        },
        "updated_at": {
          "name": "updated_at",
          "type": "timestamp with time zone",
          "primaryKey": false,
          "notNull": true,
          "default": "now()"
        }
      },
      "indexes": {},
      "foreignKeys": {},
      "compositePrimaryKeys": {},
      "uniqueConstraints": {},
      "policies": {},
      "checkConstraints": {},
      "isRLSEnabled": false
    },
    "public.subscriptions": {
      "name": "subscriptions",
      "schema": "",
      "columns": {
        "id": {
          "name": "id",
          "type": "uuid",
          "primaryKey": true,
          "notNull": true,
          "default": "gen_random_uuid()"
        },
        "user_id": {
          "name": "user_id",
          "type": "uuid",
          "primaryKey": false,
          "notNull": true
        },
        "plan_id": {
          "name": "plan_id",
          "type": "uuid",
          "primaryKey": false,
          "notNull": true
        },
        "status": {
          "name": "status",
          "type": "subscription_status",
          "typeSchema": "public",
          "primaryKey": false,
          "notNull": true,
          "default": "'active'"
        },
        "billing_cycle": {
          "name": "billing_cycle",
          "type": "billing_cycle",
          "typeSchema": "public",
          "primaryKey": false,
          "notNull": true,
          "default": "'monthly'"
        },
        "amount": {
          "name": "amount",
          "type": "numeric(10, 2)",
          "primaryKey": false,
          "notNull": true
        },
        "currency": {
          "name": "currency",
          "type": "varchar(3)",
          "primaryKey": false,
          "notNull": true,
          "default": "'TRY'"
        },
        "payment_method": {
          "name": "payment_method",
          "type": "varchar(50)",
          "primaryKey": false,
          "notNull": false
        },
        "external_subscription_id": {
          "name": "external_subscription_id",
          "type": "varchar(255)",
          "primaryKey": false,
          "notNull": false
        },
        "payment_gateway": {
          "name": "payment_gateway",
          "type": "varchar(50)",
          "primaryKey": false,
          "notNull": false
        },
        "gateway_data": {
          "name": "gateway_data",
          "type": "jsonb",
          "primaryKey": false,
          "notNull": false
        },
        "current_period_start": {
          "name": "current_period_start",
          "type": "timestamp with time zone",
          "primaryKey": false,
          "notNull": true
        },
        "current_period_end": {
          "name": "current_period_end",
          "type": "timestamp with time zone",
          "primaryKey": false,
          "notNull": true
        },
        "trial_start": {
          "name": "trial_start",
          "type": "timestamp with time zone",
          "primaryKey": false,
          "notNull": false
        },
        "trial_end": {
          "name": "trial_end",
          "type": "timestamp with time zone",
          "primaryKey": false,
          "notNull": false
        },
        "cancelled_at": {
          "name": "cancelled_at",
          "type": "timestamp with time zone",
          "primaryKey": false,
          "notNull": false
        },
        "cancel_reason": {
          "name": "cancel_reason",
          "type": "text",
          "primaryKey": false,
          "notNull": false
        },
        "created_at": {
          "name": "created_at",
          "type": "timestamp with time zone",
          "primaryKey": false,
          "notNull": true,
          "default": "now()"
        },
        "updated_at": {
          "name": "updated_at",
          "type": "timestamp with time zone",
          "primaryKey": false,
          "notNull": true,
          "default": "now()"
        }
      },
      "indexes": {
        "subscriptions_user_id_idx": {
          "name": "subscriptions_user_id_idx",
          "columns": [
            {
              "expression": "user_id",
              "isExpression": false,
              "asc": true,
              "nulls": "last"
            }
          ],
          "isUnique": false,
          "concurrently": false,
          "method": "btree",
          "with": {}
        },
        "subscriptions_plan_id_idx": {
          "name": "subscriptions_plan_id_idx",
          "columns": [
            {
              "expression": "plan_id",
              "isExpression": false,
              "asc": true,
              "nulls": "last"
            }
          ],
          "isUnique": false,
          "concurrently": false,
          "method": "btree",
          "with": {}
        },
        "subscriptions_status_idx": {
          "name": "subscriptions_status_idx",
          "columns": [
            {
              "expression": "status",
              "isExpression": false,
              "asc": true,
              "nulls": "last"
            }
          ],
          "isUnique": false,
          "concurrently": false,
          "method": "btree",
          "with": {}
        },
        "subscriptions_external_id_idx": {
          "name": "subscriptions_external_id_idx",
          "columns": [
            {
              "expression": "external_subscription_id",
              "isExpression": false,
              "asc": true,
              "nulls": "last"
            }
          ],
          "isUnique": false,
          "concurrently": false,
          "method": "btree",
          "with": {}
        },
        "subscriptions_period_idx": {
          "name": "subscriptions_period_idx",
          "columns": [
            {
              "expression": "current_period_start",
              "isExpression": false,
              "asc": true,
              "nulls": "last"
            },
            {
              "expression": "current_period_end",
              "isExpression": false,
              "asc": true,
              "nulls": "last"
            }
          ],
          "isUnique": false,
          "concurrently": false,
          "method": "btree",
          "with": {}
        }
      },
      "foreignKeys": {
        "subscriptions_user_id_users_id_fk": {
          "name": "subscriptions_user_id_users_id_fk",
          "tableFrom": "subscriptions",
          "tableTo": "users",
          "columnsFrom": [
            "user_id"
          ],
          "columnsTo": [
            "id"
          ],
          "onDelete": "no action",
          "onUpdate": "no action"
        },
        "subscriptions_plan_id_subscription_plans_id_fk": {
          "name": "subscriptions_plan_id_subscription_plans_id_fk",
          "tableFrom": "subscriptions",
          "tableTo": "subscription_plans",
          "columnsFrom": [
            "plan_id"
          ],
          "columnsTo": [
            "id"
          ],
          "onDelete": "no action",
          "onUpdate": "no action"
        }
      },
      "compositePrimaryKeys": {},
      "uniqueConstraints": {},
      "policies": {},
      "checkConstraints": {},
      "isRLSEnabled": false
    },
    "public.payments": {
      "name": "payments",
      "schema": "",
      "columns": {
        "id": {
          "name": "id",
          "type": "uuid",
          "primaryKey": true,
          "notNull": true,
          "default": "gen_random_uuid()"
        },
        "user_id": {
          "name": "user_id",
          "type": "uuid",
          "primaryKey": false,
          "notNull": true
        },
        "subscription_id": {
          "name": "subscription_id",
          "type": "uuid",
          "primaryKey": false,
          "notNull": false
        },
        "type": {
          "name": "type",
          "type": "payment_type",
          "typeSchema": "public",
          "primaryKey": false,
          "notNull": true
        },
        "status": {
          "name": "status",
          "type": "payment_status",
          "typeSchema": "public",
          "primaryKey": false,
          "notNull": true,
          "default": "'pending'"
        },
        "amount": {
          "name": "amount",
          "type": "numeric(10, 2)",
          "primaryKey": false,
          "notNull": true
        },
        "currency": {
          "name": "currency",
          "type": "varchar(3)",
          "primaryKey": false,
          "notNull": true,
          "default": "'TRY'"
        },
        "external_payment_id": {
          "name": "external_payment_id",
          "type": "varchar(255)",
          "primaryKey": false,
          "notNull": false
        },
        "payment_gateway": {
          "name": "payment_gateway",
          "type": "varchar(50)",
          "primaryKey": false,
          "notNull": true
        },
        "payment_method": {
          "name": "payment_method",
          "type": "varchar(50)",
          "primaryKey": false,
          "notNull": false
        },
        "gateway_response": {
          "name": "gateway_response",
          "type": "jsonb",
          "primaryKey": false,
          "notNull": false
        },
        "gateway_fees": {
          "name": "gateway_fees",
          "type": "numeric(10, 2)",
          "primaryKey": false,
          "notNull": false
        },
        "invoice_number": {
          "name": "invoice_number",
          "type": "varchar(100)",
          "primaryKey": false,
          "notNull": false
        },
        "receipt_url": {
          "name": "receipt_url",
          "type": "varchar(500)",
          "primaryKey": false,
          "notNull": false
        },
        "card_last4": {
          "name": "card_last4",
          "type": "varchar(4)",
          "primaryKey": false,
          "notNull": false
        },
        "card_brand": {
          "name": "card_brand",
          "type": "varchar(20)",
          "primaryKey": false,
          "notNull": false
        },
        "failure_code": {
          "name": "failure_code",
          "type": "varchar(50)",
          "primaryKey": false,
          "notNull": false
        },
        "failure_message": {
          "name": "failure_message",
          "type": "text",
          "primaryKey": false,
          "notNull": false
        },
        "refunded_amount": {
          "name": "refunded_amount",
          "type": "numeric(10, 2)",
          "primaryKey": false,
          "notNull": false
        },
        "refunded_at": {
          "name": "refunded_at",
          "type": "timestamp with time zone",
          "primaryKey": false,
          "notNull": false
        },
        "refund_reason": {
          "name": "refund_reason",
          "type": "text",
          "primaryKey": false,
          "notNull": false
        },
        "processed_at": {
          "name": "processed_at",
          "type": "timestamp with time zone",
          "primaryKey": false,
          "notNull": false
        },
        "created_at": {
          "name": "created_at",
          "type": "timestamp with time zone",
          "primaryKey": false,
          "notNull": true,
          "default": "now()"
        },
        "updated_at": {
          "name": "updated_at",
          "type": "timestamp with time zone",
          "primaryKey": false,
          "notNull": true,
          "default": "now()"
        }
      },
      "indexes": {
        "payments_user_id_idx": {
          "name": "payments_user_id_idx",
          "columns": [
            {
              "expression": "user_id",
              "isExpression": false,
              "asc": true,
              "nulls": "last"
            }
          ],
          "isUnique": false,
          "concurrently": false,
          "method": "btree",
          "with": {}
        },
        "payments_subscription_id_idx": {
          "name": "payments_subscription_id_idx",
          "columns": [
            {
              "expression": "subscription_id",
              "isExpression": false,
              "asc": true,
              "nulls": "last"
            }
          ],
          "isUnique": false,
          "concurrently": false,
          "method": "btree",
          "with": {}
        },
        "payments_status_idx": {
          "name": "payments_status_idx",
          "columns": [
            {
              "expression": "status",
              "isExpression": false,
              "asc": true,
              "nulls": "last"
            }
          ],
          "isUnique": false,
          "concurrently": false,
          "method": "btree",
          "with": {}
        },
        "payments_external_id_idx": {
          "name": "payments_external_id_idx",
          "columns": [
            {
              "expression": "external_payment_id",
              "isExpression": false,
              "asc": true,
              "nulls": "last"
            }
          ],
          "isUnique": false,
          "concurrently": false,
          "method": "btree",
          "with": {}
        },
        "payments_invoice_idx": {
          "name": "payments_invoice_idx",
          "columns": [
            {
              "expression": "invoice_number",
              "isExpression": false,
              "asc": true,
              "nulls": "last"
            }
          ],
          "isUnique": false,
          "concurrently": false,
          "method": "btree",
          "with": {}
        },
        "payments_type_status_idx": {
          "name": "payments_type_status_idx",
          "columns": [
            {
              "expression": "type",
              "isExpression": false,
              "asc": true,
              "nulls": "last"
            },
            {
              "expression": "status",
              "isExpression": false,
              "asc": true,
              "nulls": "last"
            }
          ],
          "isUnique": false,
          "concurrently": false,
          "method": "btree",
          "with": {}
        }
      },
      "foreignKeys": {
        "payments_user_id_users_id_fk": {
          "name": "payments_user_id_users_id_fk",
          "tableFrom": "payments",
          "tableTo": "users",
          "columnsFrom": [
            "user_id"
          ],
          "columnsTo": [
            "id"
          ],
          "onDelete": "no action",
          "onUpdate": "no action"
        },
        "payments_subscription_id_subscriptions_id_fk": {
          "name": "payments_subscription_id_subscriptions_id_fk",
          "tableFrom": "payments",
          "tableTo": "subscriptions",
          "columnsFrom": [
            "subscription_id"
          ],
          "columnsTo": [
            "id"
          ],
          "onDelete": "no action",
          "onUpdate": "no action"
        }
      },
      "compositePrimaryKeys": {},
      "uniqueConstraints": {},
      "policies": {},
      "checkConstraints": {},
      "isRLSEnabled": false
    }
  },
  "enums": {
    "public.blog_status": {
      "name": "blog_status",
      "schema": "public",
      "values": [
        "draft",
        "pending",
        "approved",
        "published",
        "rejected"
      ]
    },
    "public.blog_type": {
      "name": "blog_type",
      "schema": "public",
      "values": [
        "editorial",
        "owner",
        "collection"
      ]
    },
    "public.user_status": {
      "name": "user_status",
      "schema": "public",
      "values": [
        "active",
        "suspended",
        "pending"
      ]
    },
    "public.user_type": {
      "name": "user_type",
      "schema": "public",
      "values": [
        "traveler",
        "owner",
        "admin"
      ]
    },
    "public.place_status": {
      "name": "place_status",
      "schema": "public",
      "values": [
        "draft",
        "pending",
        "approved",
        "rejected",
        "suspended"
      ]
    },
    "public.place_type": {
      "name": "place_type",
      "schema": "public",
      "values": [
        "hotel",
        "restaurant",
        "villa",
        "flat",
        "activity"
      ]
    },
    "public.billing_cycle": {
      "name": "billing_cycle",
      "schema": "public",
      "values": [
        "monthly",
        "yearly"
      ]
    },
    "public.plan_type": {
      "name": "plan_type",
      "schema": "public",
      "values": [
        "basic",
        "premium",
        "enterprise"
      ]
    },
    "public.subscription_status": {
      "name": "subscription_status",
      "schema": "public",
      "values": [
        "active",
        "inactive",
        "cancelled",
        "past_due",
        "paused"
      ]
    },
    "public.payment_status": {
      "name": "payment_status",
      "schema": "public",
      "values": [
        "pending",
        "processing",
        "succeeded",
        "failed",
        "cancelled",
        "refunded"
      ]
    },
    "public.payment_type": {
      "name": "payment_type",
      "schema": "public",
      "values": [
        "subscription",
        "one_time",
        "refund"
      ]
    }
  },
  "schemas": {},
  "sequences": {},
  "roles": {},
  "policies": {},
  "views": {},
  "_meta": {
    "columns": {},
    "schemas": {},
    "tables": {}
  }
}